anekos/__init__.py
anekos/client.py
anekos/enumeration.py
anekos/errors.py
anekos/http_client.py
anekos/result.py
anekos-2.0.0.dist-info/LICENSE
anekos-2.0.0.dist-info/METADATA
anekos-2.0.0.dist-info/WHEEL
anekos-2.0.0.dist-info/top_level.txt
anekos-2.0.0.dist-info/RECORD
