Metadata-Version: 2.1
Name: anekos
Version: 2.0.0
Summary: An unofficial asynchronous wrapper for nekos.life API
Author: NiumXp
License: MIT
Project-URL: Website, https://nekos.life
Project-URL: Issue tracker, https://github.com/Nekos-life/Async-nekos.life-wrapper
Classifier: Development Status :: 5 - Production/Stable
Classifier: License :: OSI Approved :: MIT License
Classifier: Intended Audience :: Developers
Classifier: Natural Language :: English
Classifier: Operating System :: OS Independent
Classifier: Programming Language :: Python :: 3.6
Classifier: Programming Language :: Python :: 3.7
Classifier: Programming Language :: Python :: 3.8
Classifier: Programming Language :: Python :: 3.9
Classifier: Programming Language :: Python :: 3.10
Classifier: Topic :: Internet
Classifier: Topic :: Software Development :: Libraries
Classifier: Topic :: Utilities
Requires-Python: >=3.6.0
License-File: LICENSE
Requires-Dist: aiohttp (<4,>=3.6.0)
